vesta_integration_tests/__init__.py
vesta_integration_tests/__meta__.py
vesta_integration_tests/exceptions.py
vesta_integration_tests/mss_simple.py
vesta_integration_tests/mss_test.py
vesta_integration_tests/sg_test.py
vesta_integration_tests/tests_base.py
vesta_integration_tests/validate_requests.py
vesta_integration_tests-0.1.0.dist-info/DESCRIPTION.rst
vesta_integration_tests-0.1.0.dist-info/METADATA
vesta_integration_tests-0.1.0.dist-info/RECORD
vesta_integration_tests-0.1.0.dist-info/WHEEL
vesta_integration_tests-0.1.0.dist-info/entry_points.txt
vesta_integration_tests-0.1.0.dist-info/metadata.json
vesta_integration_tests-0.1.0.dist-info/top_level.txt
