Metadata-Version: 2.0
Name: vesta-integration-tests
Version: 0.1.0
Summary: Integration tests to check proper interaction between Vesta Services components.
Home-page: https://github.com/osterrfr-crim/vesta_integration_tests
Author: Fred Osterrath
Author-email: osterrfr@crim.ca
License: ISCL
Keywords: vesta_integration_tests
Platform: linux_x86_64
Classifier: Development Status :: 2 - Pre-Alpha
Classifier: Intended Audience :: Developers
Classifier: License :: OSI Approved :: ISC License (ISCL)
Classifier: Natural Language :: English
Classifier: Programming Language :: Python :: 2
Classifier: Programming Language :: Python :: 2.7
Classifier: Programming Language :: Python :: 3
Classifier: Programming Language :: Python :: 3.5
Requires-Dist: VestaRestPackage
